akind.py
akind-0.1.dist-info/METADATA
akind-0.1.dist-info/WHEEL
akind-0.1.dist-info/entry_points.txt
akind-0.1.dist-info/top_level.txt
akind-0.1.dist-info/RECORD
